CHANGES.txt
LICENSE
MANIFEST.in
README.rst
setup.cfg
setup.py
version.py
docs/Makefile
docs/advanced_usage.rst
docs/conf.py
docs/examples.rst
docs/index.rst
docs/install.rst
docs/involved.rst
docs/templates.rst
docs/test.rst
docs/use.rst
dts_test_project/.gitignore
dts_test_project/manage.py
dts_test_project/customers/__init__.py
dts_test_project/customers/models.py
dts_test_project/dts_test_app/__init__.py
dts_test_project/dts_test_app/models.py
dts_test_project/dts_test_app/migrations/0001_initial.py
dts_test_project/dts_test_app/migrations/0002_test_drop_unique.py
dts_test_project/dts_test_app/migrations/0003_test_add_db_index.py
dts_test_project/dts_test_app/migrations/0004_test_alter_unique.py
dts_test_project/dts_test_app/migrations/__init__.py
dts_test_project/dts_test_project/__init__.py
dts_test_project/dts_test_project/settings.py
dts_test_project/dts_test_project/urls.py
examples/tenant_tutorial/manage.py
examples/tenant_tutorial/customers/__init__.py
examples/tenant_tutorial/customers/forms.py
examples/tenant_tutorial/customers/models.py
examples/tenant_tutorial/customers/views.py
examples/tenant_tutorial/customers/migrations/0001_initial.py
examples/tenant_tutorial/customers/migrations/__init__.py
examples/tenant_tutorial/templates/base.html
examples/tenant_tutorial/templates/index_public.html
examples/tenant_tutorial/templates/index_tenant.html
examples/tenant_tutorial/tenant_tutorial/__init__.py
examples/tenant_tutorial/tenant_tutorial/middleware.py
examples/tenant_tutorial/tenant_tutorial/settings.py
examples/tenant_tutorial/tenant_tutorial/urls_public.py
examples/tenant_tutorial/tenant_tutorial/urls_tenants.py
examples/tenant_tutorial/tenant_tutorial/views.py
examples/tenant_tutorial/tenant_tutorial/wsgi.py
joboti_tenant_schemas.egg-info/PKG-INFO
joboti_tenant_schemas.egg-info/SOURCES.txt
joboti_tenant_schemas.egg-info/dependency_links.txt
joboti_tenant_schemas.egg-info/not-zip-safe
joboti_tenant_schemas.egg-info/requires.txt
joboti_tenant_schemas.egg-info/top_level.txt
tenant_schemas/__init__.py
tenant_schemas/apps.py
tenant_schemas/cache.py
tenant_schemas/log.py
tenant_schemas/middleware.py
tenant_schemas/models.py
tenant_schemas/routers.py
tenant_schemas/signals.py
tenant_schemas/storage.py
