Metadata-Version: 1.1
Name: joboti-tenant-schemas
Version: 1.4
Summary: Remove postgis as original backend and added search_set support
Home-page: https://github.com/joboti-com/django-tenant-schemas
Author: Ilyes Ahmed Hammadi
Author-email: hammadiilyesahmed@gmail.com
License: MIT
Platform: UNKNOWN
Classifier: License :: OSI Approved :: MIT License
Classifier: Framework :: Django
Classifier: Framework :: Django :: 1.8
Classifier: Framework :: Django :: 1.9
Classifier: Framework :: Django :: 1.10
Classifier: Programming Language :: Python
Classifier: Programming Language :: Python :: 2.7
Classifier: Programming Language :: Python :: 3.5
Classifier: Topic :: Database
Classifier: Topic :: Software Development :: Libraries
